azure_blob_logger_async/__init__.py
azure_blob_logger_async/async_blob_log_handler.py
azure_blob_logger_async/example.py
azure_blob_logger_async/logger_setup.py
azure_blob_logger_async/version.py
tool_optimus_log_collector-0.1.1.dist-info/METADATA
tool_optimus_log_collector-0.1.1.dist-info/WHEEL
tool_optimus_log_collector-0.1.1.dist-info/top_level.txt
tool_optimus_log_collector-0.1.1.dist-info/RECORD
