Metadata-Version: 2.4
Name: tool-optimus-log-collector
Version: 0.1.1
Summary: Async logging collector service for Azure Blob Storage
Home-page: https://github.com/WZBDCZ_gme/GM-GPD-DevTest/TOOL_OPTIMUS_LOG_COLLECTOR
Author: Your Name
Author-email: manish.kokse@gm.com
Classifier: Programming Language :: Python :: 3
Classifier: License :: OSI Approved :: MIT License
Classifier: Operating System :: OS Independent
Requires-Python: >=3.8
Requires-Dist: fastapi
Requires-Dist: uvicorn
Requires-Dist: azure-storage-blob
Requires-Dist: azure-identity
